queryhunter/__init__.py
queryhunter/context_manager.py
queryhunter/middleware.py
queryhunter/queryhunter.py
queryhunter/reporting.py
queryhunter/tests/__init__.py
queryhunter/tests/migrations/0001_initial.py
queryhunter/tests/migrations/__init__.py
queryhunter/tests/models.py
queryhunter/tests/my_module.py
queryhunter/tests/tests.py
queryhunter/tests/urls.py
queryhunter/tests/views.py
django_queryhunter-1.1.0.dist-info/LICENSE
django_queryhunter-1.1.0.dist-info/METADATA
django_queryhunter-1.1.0.dist-info/WHEEL
django_queryhunter-1.1.0.dist-info/RECORD
