Metadata-Version: 2.3
Name: django-queryhunter
Version: 1.1.0
Summary: Map your Django application code to the SQL queries it produces.
License: BSD-3-Clause
Author: Paul Gilmartin
Requires-Python: >=3.8.0,<4
Classifier: Framework :: Django
Classifier: Intended Audience :: Developers
Classifier: License :: OSI Approved :: BSD License
Classifier: Operating System :: OS Independent
Classifier: Programming Language :: Python
Classifier: Programming Language :: Python :: 3
Classifier: Programming Language :: Python :: 3.8
Classifier: Programming Language :: Python :: 3.9
Classifier: Programming Language :: Python :: 3.10
Classifier: Programming Language :: Python :: 3.11
Classifier: Programming Language :: Python :: 3.12
Classifier: Programming Language :: Python :: 3.13
Classifier: Programming Language :: Python :: 3 :: Only
Requires-Dist: django (>=3.2)
Project-URL: Homepage, https://github.com/PaulGilmartin/django-queryhunter
Project-URL: Repository, https://github.com/PaulGilmartin/django-queryhunter
